MANIFEST.in
README.md
setup.py
kubectl_secret_ide/__init__.py
kubectl_secret_ide/main.py
kubectl_secret_ide.egg-info/PKG-INFO
kubectl_secret_ide.egg-info/SOURCES.txt
kubectl_secret_ide.egg-info/dependency_links.txt
kubectl_secret_ide.egg-info/entry_points.txt
kubectl_secret_ide.egg-info/not-zip-safe
kubectl_secret_ide.egg-info/top_level.txt