Metadata-Version: 1.1
Name: kubectl-secret-ide
Version: 0.1
Summary: A tool to edit secrets inside k8s
Home-page: UNKNOWN
Author: Ben Antony
Author-email: antony@synyx.de
License: MIT
Keywords: kubectl kubectl-plugin k8s secrets
Platform: UNKNOWN
Classifier: License :: OSI Approved :: MIT License
Classifier: Programming Language :: Python :: 3.9
